{"game_id":"401820756","date":"2026-02-21","n_ot":0,"home":{"abbr":"LOU","name":"Louisville Cardinals","score":87,"players":[{"id":"5101761","name":"Mikel Brown Jr.","starter":true,"dnp":false,"min":31,"ortg":114.2,"pts":19,"fg":"5-10","3pt":"3-7","ft":"6-6","reb":4,"oreb":0,"dreb":4,"ast":2,"stl":2,"blk":0,"to":4,"pf":2},{"id":"5107157","name":"Ryan Conwell","starter":true,"dnp":false,"min":30,"ortg":97.9,"pts":15,"fg":"5-11","3pt":"2-7","ft":"3-3","reb":1,"oreb":1,"dreb":0,"ast":4,"stl":1,"blk":0,"to":3,"pf":1},{"id":"4702784","name":"J'Vonne Hadley","starter":true,"dnp":false,"min":27,"ortg":123.5,"pts":17,"fg":"6-11","3pt":"1-5","ft":"4-4","reb":5,"oreb":2,"dreb":3,"ast":3,"stl":2,"blk":0,"to":1,"pf":2},{"id":"4712845","name":"Isaac McKneely","starter":true,"dnp":false,"min":23,"ortg":191.3,"pts":14,"fg":"4-4","3pt":"3-3","ft":"3-3","reb":2,"oreb":0,"dreb":2,"ast":0,"stl":1,"blk":0,"to":2,"pf":1},{"id":"5311967","name":"Sananda Fru","starter":true,"dnp":false,"min":17,"ortg":40.0,"pts":2,"fg":"1-3","3pt":"0-0","ft":"0-0","reb":4,"oreb":2,"dreb":2,"ast":0,"stl":1,"blk":1,"to":2,"pf":1},{"id":"4702739","name":"Aly Khalifa","starter":false,"dnp":false,"min":17,"ortg":68.0,"pts":4,"fg":"1-3","3pt":"1-2","ft":"1-2","reb":3,"oreb":0,"dreb":3,"ast":3,"stl":1,"blk":0,"to":2,"pf":1},{"id":"4873187","name":"Khani Rooths","starter":false,"dnp":false,"min":16,"ortg":60.0,"pts":3,"fg":"1-3","3pt":"1-2","ft":"0-0","reb":2,"oreb":0,"dreb":2,"ast":0,"stl":0,"blk":0,"to":2,"pf":2},{"id":"5242127","name":"Adrian Wooley","starter":false,"dnp":false,"min":14,"ortg":75.0,"pts":3,"fg":"1-4","3pt":"1-3","ft":"0-0","reb":2,"oreb":0,"dreb":2,"ast":1,"stl":2,"blk":0,"to":0,"pf":1},{"id":"5174946","name":"Kobe Rodgers","starter":false,"dnp":false,"min":10,"ortg":180.4,"pts":7,"fg":"2-2","3pt":"1-1","ft":"2-2","reb":3,"oreb":1,"dreb":2,"ast":0,"stl":0,"blk":0,"to":1,"pf":1},{"id":"4589481","name":"Kasean Pryor","starter":false,"dnp":false,"min":7,"ortg":null,"pts":0,"fg":"0-0","3pt":"0-0","ft":"0-0","reb":1,"oreb":0,"dreb":1,"ast":1,"stl":1,"blk":1,"to":0,"pf":0},{"id":"5311969","name":"Vangelis Zougris","starter":false,"dnp":false,"min":5,"ortg":null,"pts":0,"fg":"0-0","3pt":"0-0","ft":"0-0","reb":0,"oreb":0,"dreb":0,"ast":1,"stl":0,"blk":0,"to":0,"pf":1},{"id":"5311968","name":"Will Hanke","starter":false,"dnp":false,"min":1,"ortg":null,"pts":0,"fg":"0-0","3pt":"0-0","ft":"0-0","reb":0,"oreb":0,"dreb":0,"ast":0,"stl":0,"blk":0,"to":0,"pf":0},{"id":"5106779","name":"Cole Sherman","starter":false,"dnp":false,"min":1,"ortg":0.0,"pts":0,"fg":"0-0","3pt":"0-0","ft":"0-0","reb":0,"oreb":0,"dreb":0,"ast":0,"stl":0,"blk":0,"to":1,"pf":0},{"id":"5105765","name":"Spencer Legg","starter":false,"dnp":false,"min":1,"ortg":300.0,"pts":3,"fg":"1-1","3pt":"1-1","ft":"0-0","reb":1,"oreb":0,"dreb":1,"ast":0,"stl":0,"blk":0,"to":0,"pf":0},{"id":"5311966","name":"Mouhamed Camara","starter":false,"dnp":true,"min":0,"ortg":null,"pts":0,"fg":"","3pt":"","ft":"","reb":0,"oreb":0,"dreb":0,"ast":0,"stl":0,"blk":0,"to":0,"pf":0},{"id":"5104203","name":"London Johnson","starter":false,"dnp":true,"min":0,"ortg":null,"pts":0,"fg":"","3pt":"","ft":"","reb":0,"oreb":0,"dreb":0,"ast":0,"stl":0,"blk":0,"to":0,"pf":0}],"totals":{"min":200,"pts":87,"reb":28,"oreb":6,"dreb":22,"ast":15,"stl":11,"blk":2,"to":18,"pf":13,"fgm":27,"fga":52,"tpm":14,"tpa":31,"ftm":19,"fta":20,"fg":"27-52","3pt":"14-31","ft":"19-20","fg_pct":51.9,"3pt_pct":45.2,"ft_pct":95.0,"opp_dreb":19},"four_factors":{"efg_pct":65.4,"to_pct":22.8,"or_pct":24.0,"ftr":38.5},"wab":0.104,"adj_oe":116.8,"adj_de":96.6},"away":{"abbr":"GT","name":"Georgia Tech Yellow Jackets","score":70,"players":[{"id":"5142356","name":"Baye Ndongo","starter":true,"dnp":false,"min":37,"ortg":86.0,"pts":17,"fg":"7-14","3pt":"0-2","ft":"3-4","reb":7,"oreb":4,"dreb":3,"ast":4,"stl":2,"blk":2,"to":4,"pf":4},{"id":"5106284","name":"Lamar Washington","starter":true,"dnp":false,"min":35,"ortg":80.0,"pts":12,"fg":"5-10","3pt":"2-5","ft":"0-0","reb":2,"oreb":0,"dreb":2,"ast":3,"stl":4,"blk":0,"to":5,"pf":4},{"id":"5060730","name":"Jaeden Mustaf","starter":true,"dnp":false,"min":29,"ortg":94.9,"pts":12,"fg":"3-7","3pt":"0-1","ft":"6-6","reb":1,"oreb":1,"dreb":0,"ast":1,"stl":1,"blk":0,"to":3,"pf":4},{"id":"5101784","name":"Akai Fleming","starter":true,"dnp":false,"min":28,"ortg":107.1,"pts":15,"fg":"7-13","3pt":"1-4","ft":"0-0","reb":5,"oreb":0,"dreb":5,"ast":2,"stl":1,"blk":0,"to":1,"pf":1},{"id":"4683757","name":"Kowacie Reeves Jr.","starter":true,"dnp":false,"min":20,"ortg":67.6,"pts":6,"fg":"2-7","3pt":"0-1","ft":"2-2","reb":2,"oreb":0,"dreb":2,"ast":0,"stl":0,"blk":0,"to":1,"pf":0},{"id":"5172343","name":"Cole Kirouac","starter":false,"dnp":false,"min":28,"ortg":200.0,"pts":6,"fg":"3-3","3pt":"0-0","ft":"0-0","reb":11,"oreb":4,"dreb":7,"ast":1,"stl":1,"blk":0,"to":0,"pf":2},{"id":"4888733","name":"Chas Kelley III","starter":false,"dnp":false,"min":16,"ortg":50.0,"pts":2,"fg":"1-3","3pt":"0-2","ft":"0-0","reb":1,"oreb":1,"dreb":0,"ast":2,"stl":0,"blk":0,"to":1,"pf":0},{"id":"5105607","name":"Kam Craft","starter":false,"dnp":false,"min":7,"ortg":0.0,"pts":0,"fg":"0-4","3pt":"0-3","ft":"0-0","reb":0,"oreb":0,"dreb":0,"ast":0,"stl":0,"blk":0,"to":1,"pf":1},{"id":"5258494","name":"Mouhamed Sylla","starter":false,"dnp":true,"min":0,"ortg":null,"pts":0,"fg":"","3pt":"","ft":"","reb":0,"oreb":0,"dreb":0,"ast":0,"stl":0,"blk":0,"to":0,"pf":0},{"id":"5061592","name":"Peyton Marshall","starter":false,"dnp":true,"min":0,"ortg":null,"pts":0,"fg":"","3pt":"","ft":"","reb":0,"oreb":0,"dreb":0,"ast":0,"stl":0,"blk":0,"to":0,"pf":0},{"id":"5311960","name":"Davi Remagen","starter":false,"dnp":true,"min":0,"ortg":null,"pts":0,"fg":"","3pt":"","ft":"","reb":0,"oreb":0,"dreb":0,"ast":0,"stl":0,"blk":0,"to":0,"pf":0},{"id":"5248298","name":"Eric Chatfield Jr.","starter":false,"dnp":true,"min":0,"ortg":null,"pts":0,"fg":"","3pt":"","ft":"","reb":0,"oreb":0,"dreb":0,"ast":0,"stl":0,"blk":0,"to":0,"pf":0},{"id":"5238167","name":"Dyllan Thompson","starter":false,"dnp":true,"min":0,"ortg":null,"pts":0,"fg":"","3pt":"","ft":"","reb":0,"oreb":0,"dreb":0,"ast":0,"stl":0,"blk":0,"to":0,"pf":0},{"id":"5144109","name":"Brandon Stores Jr.","starter":false,"dnp":true,"min":0,"ortg":null,"pts":0,"fg":"","3pt":"","ft":"","reb":0,"oreb":0,"dreb":0,"ast":0,"stl":0,"blk":0,"to":0,"pf":0}],"totals":{"min":200,"pts":70,"reb":29,"oreb":10,"dreb":19,"ast":13,"stl":9,"blk":2,"to":16,"pf":16,"fgm":28,"fga":61,"tpm":3,"tpa":18,"ftm":11,"fta":12,"fg":"28-61","3pt":"3-18","ft":"11-12","fg_pct":45.9,"3pt_pct":16.7,"ft_pct":91.7,"opp_dreb":22},"four_factors":{"efg_pct":48.4,"to_pct":19.4,"or_pct":31.2,"ftr":19.7},"wab":-0.186,"adj_oe":96.6,"adj_de":116.8},"tempo":73.5,"poss":73.5,"spread":22.1,"wp":[{"t":2400,"wp":85.1,"hs":0,"as":0,"p":1,"text":"Game Start"},{"t":2389,"wp":87.0,"hs":2,"as":0,"p":1,"text":"Sananda Fru makes 5-foot dunk (Ryan Conwell assists)"},{"t":2361,"wp":85.3,"hs":2,"as":2,"p":1,"text":"Kowacie Reeves Jr. makes 10-foot floating jump shot"},{"t":2334,"wp":88.2,"hs":5,"as":2,"p":1,"text":"Isaac McKneely makes 24-foot three point jumper (J'Vonne Hadley assists)"},{"t":2306,"wp":86.6,"hs":5,"as":4,"p":1,"text":"Baye Ndongo makes 15-foot jumper (Lamar Washington assists)"},{"t":2289,"wp":88.5,"hs":7,"as":4,"p":1,"text":"Ryan Conwell makes driving layup"},{"t":2267,"wp":86.8,"hs":7,"as":6,"p":1,"text":"Baye Ndongo makes 0-foot tip in layup"},{"t":2252,"wp":88.7,"hs":9,"as":6,"p":1,"text":"J'Vonne Hadley makes 5-foot jumper"},{"t":2234,"wp":87.0,"hs":9,"as":8,"p":1,"text":"Jaeden Mustaf makes driving layup"},{"t":2224,"wp":89.8,"hs":12,"as":8,"p":1,"text":"Mikel Brown Jr. makes 27-foot three pointer"},{"t":2175,"wp":88.3,"hs":12,"as":10,"p":1,"text":"Akai Fleming makes 12-foot pullup jump shot"},{"t":2154,"wp":91.0,"hs":15,"as":10,"p":1,"text":"Mikel Brown Jr. makes 24-foot three point step back jumpshot"},{"t":2032,"wp":92.5,"hs":16,"as":10,"p":1,"text":"Isaac McKneely makes free throw 1 of 3"},{"t":2032,"wp":93.2,"hs":17,"as":10,"p":1,"text":"Isaac McKneely makes free throw 2 of 3"},{"t":2032,"wp":93.9,"hs":18,"as":10,"p":1,"text":"Isaac McKneely makes free throw 3 of 3"},{"t":2015,"wp":94.6,"hs":19,"as":10,"p":1,"text":"Mikel Brown Jr. makes free throw 1 of 2"},{"t":2015,"wp":95.1,"hs":20,"as":10,"p":1,"text":"Mikel Brown Jr. makes free throw 2 of 2"},{"t":1856,"wp":96.5,"hs":21,"as":10,"p":1,"text":"Kobe Rodgers makes free throw 1 of 2"},{"t":1856,"wp":96.9,"hs":22,"as":10,"p":1,"text":"Kobe Rodgers makes free throw 2 of 2"},{"t":1844,"wp":96.1,"hs":22,"as":12,"p":1,"text":"Jaeden Mustaf makes layup (Baye Ndongo assists)"},{"t":1796,"wp":97.6,"hs":25,"as":12,"p":1,"text":"Kobe Rodgers makes 26-foot three point jumper (Mikel Brown Jr. assists)"},{"t":1761,"wp":98.6,"hs":28,"as":12,"p":1,"text":"Adrian Wooley makes 24-foot three point jumper (Ryan Conwell assists)"},{"t":1732,"wp":98.2,"hs":28,"as":14,"p":1,"text":"Lamar Washington makes layup (Akai Fleming assists)"},{"t":1690,"wp":98.8,"hs":30,"as":14,"p":1,"text":"J'Vonne Hadley makes layup (Adrian Wooley assists)"},{"t":1674,"wp":98.4,"hs":30,"as":16,"p":1,"text":"Baye Ndongo makes layup (Akai Fleming assists)"},{"t":1643,"wp":97.5,"hs":30,"as":19,"p":1,"text":"Akai Fleming makes 26-foot three point jumper (Lamar Washington assists)"},{"t":1610,"wp":98.6,"hs":33,"as":19,"p":1,"text":"J'Vonne Hadley makes 24-foot three point jumper (Vangelis Zougris assists)"},{"t":1549,"wp":99.0,"hs":34,"as":19,"p":1,"text":"Mikel Brown Jr. makes free throw 1 of 2"},{"t":1549,"wp":99.2,"hs":35,"as":19,"p":1,"text":"Mikel Brown Jr. makes free throw 2 of 2"},{"t":1523,"wp":99.5,"hs":37,"as":19,"p":1,"text":"Isaac McKneely makes layup"},{"t":1439,"wp":99.4,"hs":37,"as":21,"p":1,"text":"Chas Kelley III makes 12-foot pullup jump shot"},{"t":1405,"wp":99.1,"hs":37,"as":23,"p":1,"text":"Baye Ndongo makes 0-foot tip in layup"},{"t":1334,"wp":98.6,"hs":37,"as":26,"p":1,"text":"Lamar Washington makes 25-foot three point jumper (Baye Ndongo assists)"},{"t":1298,"wp":97.9,"hs":37,"as":28,"p":1,"text":"Baye Ndongo makes 4-foot hook shot (Chas Kelley III assists)"},{"t":1253,"wp":96.3,"hs":37,"as":31,"p":1,"text":"Lamar Washington makes 24-foot three point jumper (Chas Kelley III assists)"},{"t":1239,"wp":97.6,"hs":39,"as":31,"p":1,"text":"J'Vonne Hadley makes 0-foot tip in layup"},{"t":1202,"wp":98.9,"hs":42,"as":31,"p":1,"text":"Ryan Conwell makes 24-foot three point step back jumpshot"},{"t":1200,"wp":98.9,"hs":42,"as":31,"p":1,"text":"End of 1st half"},{"t":1184,"wp":98.3,"hs":42,"as":33,"p":2,"text":"Akai Fleming makes 18-foot step back jumpshot"},{"t":1140,"wp":99.0,"hs":44,"as":33,"p":2,"text":"J'Vonne Hadley makes layup"},{"t":1110,"wp":98.5,"hs":44,"as":35,"p":2,"text":"Kowacie Reeves Jr. makes driving layup"},{"t":1080,"wp":98.9,"hs":45,"as":35,"p":2,"text":"J'Vonne Hadley makes free throw 1 of 2"},{"t":1080,"wp":99.2,"hs":46,"as":35,"p":2,"text":"J'Vonne Hadley makes free throw 2 of 2"},{"t":1012,"wp":99.6,"hs":48,"as":35,"p":2,"text":"Mikel Brown Jr. makes driving layup"},{"t":954,"wp":99.6,"hs":48,"as":36,"p":2,"text":"Kowacie Reeves Jr. makes free throw 1 of 2"},{"t":954,"wp":99.4,"hs":48,"as":37,"p":2,"text":"Kowacie Reeves Jr. makes free throw 2 of 2"},{"t":928,"wp":99.8,"hs":51,"as":37,"p":2,"text":"Khani Rooths makes 24-foot three point jumper (Aly Khalifa assists)"},{"t":870,"wp":99.9,"hs":53,"as":37,"p":2,"text":"Kobe Rodgers makes 0-foot tip in layup"},{"t":839,"wp":100.0,"hs":55,"as":37,"p":2,"text":"Ryan Conwell makes layup (Aly Khalifa assists)"},{"t":839,"wp":100.0,"hs":56,"as":37,"p":2,"text":"Ryan Conwell makes free throw 1 of 1"},{"t":782,"wp":100.0,"hs":58,"as":37,"p":2,"text":"Mikel Brown Jr. makes 21-foot jumper (Ryan Conwell assists)"},{"t":756,"wp":100.0,"hs":61,"as":37,"p":2,"text":"Mikel Brown Jr. makes 24-foot three pointer"},{"t":733,"wp":100.0,"hs":61,"as":39,"p":2,"text":"Baye Ndongo makes layup (Jaeden Mustaf assists)"},{"t":718,"wp":100.0,"hs":64,"as":39,"p":2,"text":"Aly Khalifa makes 26-foot three point jumper (J'Vonne Hadley assists)"},{"t":698,"wp":100.0,"hs":64,"as":40,"p":2,"text":"Jaeden Mustaf makes free throw 1 of 2"},{"t":698,"wp":100.0,"hs":64,"as":41,"p":2,"text":"Jaeden Mustaf makes free throw 2 of 2"},{"t":656,"wp":100.0,"hs":65,"as":41,"p":2,"text":"Mikel Brown Jr. makes free throw 1 of 2"},{"t":656,"wp":100.0,"hs":66,"as":41,"p":2,"text":"Mikel Brown Jr. makes free throw 2 of 2"},{"t":643,"wp":100.0,"hs":66,"as":43,"p":2,"text":"Akai Fleming makes 13-foot jumper (Lamar Washington assists)"},{"t":597,"wp":100.0,"hs":66,"as":45,"p":2,"text":"Cole Kirouac makes 4-foot alley oop dunk (Baye Ndongo assists)"},{"t":583,"wp":100.0,"hs":66,"as":46,"p":2,"text":"Baye Ndongo makes free throw 1 of 2"},{"t":583,"wp":100.0,"hs":66,"as":47,"p":2,"text":"Baye Ndongo makes free throw 2 of 2"},{"t":546,"wp":100.0,"hs":66,"as":49,"p":2,"text":"Cole Kirouac makes 0-foot tip in dunk"},{"t":526,"wp":100.0,"hs":66,"as":51,"p":2,"text":"Akai Fleming makes layup"},{"t":494,"wp":100.0,"hs":66,"as":53,"p":2,"text":"Cole Kirouac makes 3-foot dunk (Baye Ndongo assists)"},{"t":458,"wp":99.9,"hs":66,"as":55,"p":2,"text":"Akai Fleming makes 5-foot jumper"},{"t":450,"wp":100.0,"hs":67,"as":55,"p":2,"text":"Ryan Conwell makes free throw 1 of 2"},{"t":450,"wp":100.0,"hs":68,"as":55,"p":2,"text":"Ryan Conwell makes free throw 2 of 2"},{"t":414,"wp":99.9,"hs":68,"as":57,"p":2,"text":"Lamar Washington makes 8-foot jumper"},{"t":405,"wp":100.0,"hs":70,"as":57,"p":2,"text":"J'Vonne Hadley makes layup (Mikel Brown Jr. assists)"},{"t":384,"wp":100.0,"hs":70,"as":58,"p":2,"text":"Baye Ndongo makes free throw 1 of 2"},{"t":361,"wp":100.0,"hs":73,"as":58,"p":2,"text":"Ryan Conwell makes 25-foot three point jumper (Aly Khalifa assists)"},{"t":347,"wp":100.0,"hs":73,"as":59,"p":2,"text":"Jaeden Mustaf makes free throw 1 of 2"},{"t":347,"wp":100.0,"hs":73,"as":60,"p":2,"text":"Jaeden Mustaf makes free throw 2 of 2"},{"t":272,"wp":100.0,"hs":74,"as":60,"p":2,"text":"J'Vonne Hadley makes free throw 1 of 2"},{"t":272,"wp":100.0,"hs":75,"as":60,"p":2,"text":"J'Vonne Hadley makes free throw 2 of 2"},{"t":259,"wp":100.0,"hs":75,"as":61,"p":2,"text":"Jaeden Mustaf makes free throw 1 of 2"},{"t":259,"wp":100.0,"hs":75,"as":62,"p":2,"text":"Jaeden Mustaf makes free throw 2 of 2"},{"t":230,"wp":100.0,"hs":78,"as":62,"p":2,"text":"Isaac McKneely makes 28-foot three point jumper (J'Vonne Hadley assists)"},{"t":180,"wp":100.0,"hs":79,"as":62,"p":2,"text":"Aly Khalifa makes free throw 2 of 2"},{"t":162,"wp":100.0,"hs":79,"as":64,"p":2,"text":"Jaeden Mustaf makes 14-foot pullup jump shot"},{"t":140,"wp":100.0,"hs":82,"as":64,"p":2,"text":"Isaac McKneely makes 25-foot three point jumper (Ryan Conwell assists)"},{"t":116,"wp":100.0,"hs":82,"as":66,"p":2,"text":"Lamar Washington makes 8-foot jumper"},{"t":65,"wp":100.0,"hs":84,"as":66,"p":2,"text":"Ryan Conwell makes 9-foot floating jump shot"},{"t":43,"wp":100.0,"hs":84,"as":68,"p":2,"text":"Akai Fleming makes 3-foot dunk (Cole Kirouac assists)"},{"t":29,"wp":100.0,"hs":87,"as":68,"p":2,"text":"Spencer Legg makes 28-foot three point jumper (Kasean Pryor assists)"},{"t":16,"wp":100.0,"hs":87,"as":70,"p":2,"text":"Baye Ndongo makes 0-foot tip in dunk"},{"t":0,"wp":100.0,"hs":87,"as":70,"p":2,"text":"End of 2nd half"},{"t":0,"wp":100.0,"hs":87,"as":70,"p":2,"text":"End of Game"},{"t":0,"wp":100.0,"hs":87,"as":70,"p":2,"text":"Final"}],"runs":[{"team":"GT","run":"14-0","pts":14,"period":2,"start_clock":"10:43","end_clock":"7:38","start_score":"66-41","end_score":"66-55"},{"team":"LOU","run":"13-0","pts":13,"period":2,"start_clock":"15:28","end_clock":"12:36","start_score":"48-37","end_score":"61-37"},{"team":"GT","run":"12-0","pts":12,"period":1,"start_clock":"3:59","end_clock":"0:53","start_score":"37-19","end_score":"37-31"},{"team":"LOU","run":"10-0","pts":10,"period":1,"start_clock":"15:54","end_clock":"10:56","start_score":"12-10","end_score":"22-10"}],"lead_changes":0,"ties":3,"largest_lead":{"home":25,"away":0},"big_swings":[{"idx":3,"swing":2.9,"text":"Isaac McKneely makes 24-foot three point jumper (J'Vonne Hadley assists)","wp":88.2},{"idx":9,"swing":2.8,"text":"Mikel Brown Jr. makes 27-foot three pointer","wp":89.8},{"idx":11,"swing":2.7,"text":"Mikel Brown Jr. makes 24-foot three point step back jumpshot","wp":91.0},{"idx":1,"swing":1.9,"text":"Sananda Fru makes 5-foot dunk (Ryan Conwell assists)","wp":87.0},{"idx":5,"swing":1.9,"text":"Ryan Conwell makes driving layup","wp":88.5}]}