{"game_id":"401824825","date":"2025-11-11","n_ot":0,"home":{"abbr":"UCF","name":"UCF Knights","score":97,"players":[{"id":"5105529","name":"Riley Kugel","starter":true,"dnp":false,"min":28,"ortg":128.6,"pts":16,"fg":"6-10","3pt":"3-3","ft":"1-1","reb":0,"oreb":0,"dreb":0,"ast":2,"stl":2,"blk":1,"to":2,"pf":3},{"id":"4704078","name":"Themus Fulks","starter":true,"dnp":false,"min":21,"ortg":46.2,"pts":6,"fg":"3-9","3pt":"0-0","ft":"0-0","reb":6,"oreb":2,"dreb":4,"ast":6,"stl":1,"blk":0,"to":4,"pf":2},{"id":"5241667","name":"Jamichael Stillwell","starter":true,"dnp":false,"min":19,"ortg":102.0,"pts":6,"fg":"2-4","3pt":"1-2","ft":"1-2","reb":6,"oreb":1,"dreb":5,"ast":2,"stl":3,"blk":2,"to":1,"pf":0},{"id":"5060684","name":"Jordan Burks","starter":true,"dnp":false,"min":19,"ortg":83.6,"pts":9,"fg":"3-8","3pt":"0-2","ft":"3-4","reb":7,"oreb":2,"dreb":5,"ast":1,"stl":1,"blk":1,"to":1,"pf":4},{"id":"4915060","name":"John Bol","starter":true,"dnp":false,"min":14,"ortg":139.8,"pts":9,"fg":"4-5","3pt":"0-0","ft":"1-1","reb":5,"oreb":3,"dreb":2,"ast":0,"stl":0,"blk":0,"to":1,"pf":1},{"id":"4567588","name":"Devan Cambridge","starter":false,"dnp":false,"min":20,"ortg":232.6,"pts":8,"fg":"3-3","3pt":"1-1","ft":"1-1","reb":5,"oreb":1,"dreb":4,"ast":4,"stl":0,"blk":0,"to":0,"pf":0},{"id":"5242634","name":"Carmelo Pacheco","starter":false,"dnp":false,"min":18,"ortg":215.7,"pts":17,"fg":"5-7","3pt":"5-6","ft":"2-2","reb":1,"oreb":0,"dreb":1,"ast":1,"stl":0,"blk":0,"to":0,"pf":0},{"id":"5175069","name":"Chris Johnson","starter":false,"dnp":false,"min":13,"ortg":46.6,"pts":3,"fg":"1-4","3pt":"0-1","ft":"1-1","reb":3,"oreb":0,"dreb":3,"ast":5,"stl":3,"blk":0,"to":2,"pf":3},{"id":"5107975","name":"George Beale Jr.","starter":false,"dnp":false,"min":13,"ortg":125.0,"pts":10,"fg":"4-7","3pt":"2-4","ft":"0-0","reb":2,"oreb":1,"dreb":1,"ast":1,"stl":1,"blk":1,"to":1,"pf":2},{"id":"4848623","name":"Kris Parker","starter":false,"dnp":false,"min":13,"ortg":125.0,"pts":5,"fg":"2-3","3pt":"1-1","ft":"0-0","reb":2,"oreb":1,"dreb":1,"ast":1,"stl":0,"blk":0,"to":1,"pf":0},{"id":"5105970","name":"Jeremy Foumena","starter":false,"dnp":false,"min":10,"ortg":104.2,"pts":6,"fg":"2-3","3pt":"0-0","ft":"2-4","reb":6,"oreb":3,"dreb":3,"ast":0,"stl":0,"blk":0,"to":1,"pf":1},{"id":"5108850","name":"Elijah Hulsewe","starter":false,"dnp":false,"min":7,"ortg":null,"pts":0,"fg":"0-0","3pt":"0-0","ft":"0-0","reb":1,"oreb":0,"dreb":1,"ast":1,"stl":0,"blk":1,"to":0,"pf":1},{"id":"5106645","name":"Poohpha Warakulnukroh","starter":false,"dnp":false,"min":3,"ortg":40.0,"pts":2,"fg":"1-3","3pt":"0-0","ft":"0-0","reb":1,"oreb":0,"dreb":1,"ast":0,"stl":0,"blk":0,"to":2,"pf":0},{"id":"5311932","name":"Zach Johnson","starter":false,"dnp":false,"min":2,"ortg":null,"pts":0,"fg":"0-0","3pt":"0-0","ft":"0-0","reb":0,"oreb":0,"dreb":0,"ast":0,"stl":0,"blk":0,"to":0,"pf":0},{"id":"5311933","name":"Tanner Jones","starter":false,"dnp":true,"min":0,"ortg":null,"pts":0,"fg":"","3pt":"","ft":"","reb":0,"oreb":0,"dreb":0,"ast":0,"stl":0,"blk":0,"to":0,"pf":0}],"totals":{"min":200,"pts":97,"reb":45,"oreb":14,"dreb":31,"ast":24,"stl":11,"blk":6,"to":16,"pf":17,"fgm":36,"fga":66,"tpm":13,"tpa":20,"ftm":12,"fta":16,"fg":"36-66","3pt":"13-20","ft":"12-16","fg_pct":54.5,"3pt_pct":65.0,"ft_pct":75.0,"opp_dreb":16},"four_factors":{"efg_pct":64.4,"to_pct":18.0,"or_pct":46.7,"ftr":24.2},"wab":0.017,"adj_oe":128.4,"adj_de":82.2},"away":{"abbr":"FAMU","name":"Florida A&M Rattlers","score":60,"players":[{"id":"5325879","name":"Antonio Baker Jr.","starter":true,"dnp":false,"min":29,"ortg":53.0,"pts":6,"fg":"2-8","3pt":"0-2","ft":"2-3","reb":1,"oreb":0,"dreb":1,"ast":0,"stl":2,"blk":1,"to":2,"pf":3},{"id":"4897175","name":"Tyler Shirley","starter":true,"dnp":false,"min":24,"ortg":37.5,"pts":3,"fg":"1-4","3pt":"1-3","ft":"0-0","reb":3,"oreb":0,"dreb":3,"ast":1,"stl":0,"blk":0,"to":4,"pf":1},{"id":"5313446","name":"Miles Ndalama","starter":true,"dnp":false,"min":22,"ortg":77.5,"pts":8,"fg":"4-6","3pt":"0-0","ft":"0-3","reb":6,"oreb":2,"dreb":4,"ast":1,"stl":0,"blk":3,"to":3,"pf":3},{"id":"5105593","name":"Jaquan Sanders","starter":true,"dnp":false,"min":22,"ortg":67.2,"pts":5,"fg":"2-6","3pt":"0-2","ft":"1-1","reb":1,"oreb":1,"dreb":0,"ast":2,"stl":1,"blk":0,"to":1,"pf":0},{"id":"5177189","name":"Anquan Boldin Jr","starter":true,"dnp":false,"min":21,"ortg":41.0,"pts":4,"fg":"1-7","3pt":"0-0","ft":"2-4","reb":4,"oreb":2,"dreb":2,"ast":1,"stl":0,"blk":2,"to":1,"pf":1},{"id":"5107408","name":"Jordan Chatman","starter":false,"dnp":false,"min":22,"ortg":72.7,"pts":5,"fg":"1-4","3pt":"1-3","ft":"2-2","reb":0,"oreb":0,"dreb":0,"ast":1,"stl":0,"blk":0,"to":2,"pf":3},{"id":"5313445","name":"Devere Palmer Jr","starter":false,"dnp":false,"min":20,"ortg":127.1,"pts":9,"fg":"2-4","3pt":"0-0","ft":"5-7","reb":2,"oreb":0,"dreb":2,"ast":3,"stl":3,"blk":0,"to":0,"pf":1},{"id":"5313444","name":"Anthony Knowles","starter":false,"dnp":false,"min":17,"ortg":150.0,"pts":12,"fg":"4-8","3pt":"4-8","ft":"0-0","reb":1,"oreb":0,"dreb":1,"ast":1,"stl":0,"blk":0,"to":0,"pf":2},{"id":"4684293","name":"Kaleb Washington","starter":false,"dnp":false,"min":15,"ortg":29.1,"pts":2,"fg":"1-4","3pt":"0-2","ft":"0-2","reb":2,"oreb":0,"dreb":2,"ast":3,"stl":4,"blk":0,"to":2,"pf":0},{"id":"5323983","name":"Amir Rahman","starter":false,"dnp":false,"min":3,"ortg":200.0,"pts":4,"fg":"2-2","3pt":"0-0","ft":"0-0","reb":0,"oreb":0,"dreb":0,"ast":0,"stl":0,"blk":0,"to":0,"pf":1},{"id":"5243336","name":"Malcolm Stute","starter":false,"dnp":false,"min":3,"ortg":null,"pts":0,"fg":"0-0","3pt":"0-0","ft":"0-0","reb":0,"oreb":0,"dreb":0,"ast":2,"stl":1,"blk":0,"to":0,"pf":0},{"id":"5243337","name":"Lenard Taylor Jr.","starter":false,"dnp":false,"min":2,"ortg":66.7,"pts":2,"fg":"1-2","3pt":"0-1","ft":"0-0","reb":1,"oreb":0,"dreb":1,"ast":0,"stl":0,"blk":0,"to":1,"pf":1},{"id":"5177530","name":"Micah Octave","starter":false,"dnp":true,"min":0,"ortg":null,"pts":0,"fg":"","3pt":"","ft":"","reb":0,"oreb":0,"dreb":0,"ast":0,"stl":0,"blk":0,"to":0,"pf":0}],"totals":{"min":200,"pts":60,"reb":21,"oreb":5,"dreb":16,"ast":15,"stl":11,"blk":6,"to":16,"pf":16,"fgm":21,"fga":55,"tpm":6,"tpa":21,"ftm":12,"fta":22,"fg":"21-55","3pt":"6-21","ft":"12-22","fg_pct":38.2,"3pt_pct":28.6,"ft_pct":54.5,"opp_dreb":31},"four_factors":{"efg_pct":43.6,"to_pct":19.8,"or_pct":13.9,"ftr":40.0},"wab":-0.46,"adj_oe":82.2,"adj_de":128.4},"tempo":74.6,"poss":74.6,"spread":25.2,"wp":[{"t":2400,"wp":87.9,"hs":0,"as":0,"p":1,"text":"Game Start"},{"t":2377,"wp":89.6,"hs":2,"as":0,"p":1,"text":"Themus Fulks made Jumper. Assisted by Jordan Burks."},{"t":2354,"wp":88.1,"hs":2,"as":2,"p":1,"text":"Antonio Baker Jr. made Jumper."},{"t":2304,"wp":90.0,"hs":4,"as":2,"p":1,"text":"John Bol made Jumper. Assisted by Themus Fulks."},{"t":2253,"wp":92.4,"hs":7,"as":2,"p":1,"text":"Jamichael Stillwell made Three Point Jumper. Assisted by Themus Fulks."},{"t":2228,"wp":91.9,"hs":7,"as":3,"p":1,"text":"Anquan Boldin Jr made Free Throw."},{"t":2195,"wp":94.0,"hs":10,"as":3,"p":1,"text":"Riley Kugel made Three Point Jumper. Assisted by Jamichael Stillwell."},{"t":2155,"wp":95.2,"hs":12,"as":3,"p":1,"text":"Themus Fulks made Layup."},{"t":2116,"wp":96.3,"hs":14,"as":3,"p":1,"text":"Jeremy Foumena made Jumper. Assisted by Themus Fulks."},{"t":2042,"wp":97.3,"hs":16,"as":3,"p":1,"text":"Devan Cambridge made Layup. Assisted by Chris Johnson."},{"t":2042,"wp":97.6,"hs":17,"as":3,"p":1,"text":"Devan Cambridge made Free Throw."},{"t":1979,"wp":98.2,"hs":18,"as":3,"p":1,"text":"Jeremy Foumena made Free Throw."},{"t":1979,"wp":98.4,"hs":19,"as":3,"p":1,"text":"Jeremy Foumena made Free Throw."},{"t":1950,"wp":98.0,"hs":19,"as":5,"p":1,"text":"Miles Ndalama made Jumper. Assisted by Devere Palmer Jr."},{"t":1918,"wp":97.5,"hs":19,"as":7,"p":1,"text":"Kaleb Washington made Dunk. Assisted by Anthony Knowles."},{"t":1821,"wp":98.7,"hs":22,"as":7,"p":1,"text":"George Beale Jr. made Three Point Jumper. Assisted by Devan Cambridge."},{"t":1800,"wp":98.5,"hs":22,"as":8,"p":1,"text":"Jordan Chatman made Free Throw."},{"t":1800,"wp":98.3,"hs":22,"as":9,"p":1,"text":"Jordan Chatman made Free Throw."},{"t":1769,"wp":99.0,"hs":25,"as":9,"p":1,"text":"Riley Kugel made Three Point Jumper."},{"t":1737,"wp":99.5,"hs":28,"as":9,"p":1,"text":"Kris Parker made Three Point Jumper. Assisted by Jamichael Stillwell."},{"t":1679,"wp":99.2,"hs":28,"as":12,"p":1,"text":"Jordan Chatman made Three Point Jumper. Assisted by Devere Palmer Jr."},{"t":1660,"wp":99.5,"hs":30,"as":12,"p":1,"text":"Jamichael Stillwell made Layup. Assisted by Riley Kugel."},{"t":1589,"wp":99.7,"hs":32,"as":12,"p":1,"text":"Jordan Burks made Dunk."},{"t":1543,"wp":99.9,"hs":34,"as":12,"p":1,"text":"Jordan Burks made Dunk. Assisted by Themus Fulks."},{"t":1522,"wp":99.8,"hs":34,"as":14,"p":1,"text":"Jaquan Sanders made Jumper."},{"t":1502,"wp":99.9,"hs":36,"as":14,"p":1,"text":"Themus Fulks made Layup. Assisted by Chris Johnson."},{"t":1483,"wp":99.8,"hs":36,"as":16,"p":1,"text":"Lenard Taylor Jr. made Layup. Assisted by Jordan Chatman."},{"t":1463,"wp":99.9,"hs":38,"as":16,"p":1,"text":"Chris Johnson made Layup."},{"t":1459,"wp":99.9,"hs":39,"as":16,"p":1,"text":"Chris Johnson made Free Throw."},{"t":1429,"wp":99.9,"hs":39,"as":18,"p":1,"text":"Anquan Boldin Jr made Layup. Assisted by Kaleb Washington."},{"t":1369,"wp":100.0,"hs":42,"as":18,"p":1,"text":"Carmelo Pacheco made Three Point Jumper. Assisted by Devan Cambridge."},{"t":1338,"wp":100.0,"hs":44,"as":18,"p":1,"text":"Jeremy Foumena made Two Point Tip Shot."},{"t":1257,"wp":100.0,"hs":44,"as":20,"p":1,"text":"Miles Ndalama made Layup."},{"t":1221,"wp":100.0,"hs":45,"as":20,"p":1,"text":"Jamichael Stillwell made Free Throw."},{"t":1207,"wp":100.0,"hs":48,"as":20,"p":1,"text":"Carmelo Pacheco made Three Point Jumper. Assisted by Themus Fulks."},{"t":1200,"wp":100.0,"hs":48,"as":20,"p":1,"text":"End of 1st half"},{"t":1160,"wp":100.0,"hs":48,"as":22,"p":2,"text":"Miles Ndalama made Layup."},{"t":1070,"wp":100.0,"hs":48,"as":25,"p":2,"text":"Tyler Shirley made Three Point Jumper. Assisted by Miles Ndalama."},{"t":1061,"wp":100.0,"hs":50,"as":25,"p":2,"text":"Jordan Burks made Layup."},{"t":999,"wp":100.0,"hs":50,"as":28,"p":2,"text":"Anthony Knowles made Three Point Jumper. Assisted by Devere Palmer Jr."},{"t":979,"wp":100.0,"hs":52,"as":28,"p":2,"text":"John Bol made Two Point Tip Shot."},{"t":930,"wp":100.0,"hs":54,"as":28,"p":2,"text":"Riley Kugel made Layup. Assisted by Chris Johnson."},{"t":930,"wp":100.0,"hs":55,"as":28,"p":2,"text":"Riley Kugel made Free Throw."},{"t":911,"wp":100.0,"hs":57,"as":28,"p":2,"text":"Riley Kugel made Dunk. Assisted by Chris Johnson."},{"t":877,"wp":100.0,"hs":57,"as":30,"p":2,"text":"Devere Palmer Jr made Layup. Assisted by Kaleb Washington."},{"t":858,"wp":100.0,"hs":60,"as":30,"p":2,"text":"Devan Cambridge made Three Point Jumper. Assisted by George Beale Jr.."},{"t":838,"wp":100.0,"hs":60,"as":31,"p":2,"text":"Devere Palmer Jr made Free Throw."},{"t":838,"wp":100.0,"hs":60,"as":32,"p":2,"text":"Devere Palmer Jr made Free Throw."},{"t":798,"wp":100.0,"hs":60,"as":34,"p":2,"text":"Devere Palmer Jr made Layup."},{"t":777,"wp":100.0,"hs":62,"as":34,"p":2,"text":"Kris Parker made Layup. Assisted by Carmelo Pacheco."},{"t":761,"wp":100.0,"hs":62,"as":37,"p":2,"text":"Anthony Knowles made Three Point Jumper. Assisted by Jaquan Sanders."},{"t":745,"wp":100.0,"hs":65,"as":37,"p":2,"text":"Riley Kugel made Three Point Jumper. Assisted by Kris Parker."},{"t":732,"wp":100.0,"hs":65,"as":40,"p":2,"text":"Anthony Knowles made Three Point Jumper. Assisted by Jaquan Sanders."},{"t":709,"wp":100.0,"hs":66,"as":40,"p":2,"text":"Jordan Burks made Free Throw."},{"t":635,"wp":100.0,"hs":67,"as":40,"p":2,"text":"Jordan Burks made Free Throw."},{"t":635,"wp":100.0,"hs":68,"as":40,"p":2,"text":"Jordan Burks made Free Throw."},{"t":626,"wp":100.0,"hs":68,"as":41,"p":2,"text":"Antonio Baker Jr. made Free Throw."},{"t":626,"wp":100.0,"hs":69,"as":41,"p":2,"text":"Carmelo Pacheco made Free Throw."},{"t":626,"wp":100.0,"hs":70,"as":41,"p":2,"text":"Carmelo Pacheco made Free Throw."},{"t":607,"wp":100.0,"hs":70,"as":43,"p":2,"text":"Antonio Baker Jr. made Layup."},{"t":607,"wp":100.0,"hs":70,"as":44,"p":2,"text":"Antonio Baker Jr. made Free Throw."},{"t":586,"wp":100.0,"hs":73,"as":44,"p":2,"text":"Carmelo Pacheco made Three Point Jumper. Assisted by Devan Cambridge."},{"t":568,"wp":100.0,"hs":73,"as":46,"p":2,"text":"Miles Ndalama made Layup. Assisted by Tyler Shirley."},{"t":542,"wp":100.0,"hs":76,"as":46,"p":2,"text":"Carmelo Pacheco made Three Point Jumper. Assisted by Devan Cambridge."},{"t":523,"wp":100.0,"hs":76,"as":47,"p":2,"text":"Devere Palmer Jr made Free Throw."},{"t":523,"wp":100.0,"hs":76,"as":48,"p":2,"text":"Devere Palmer Jr made Free Throw."},{"t":514,"wp":100.0,"hs":79,"as":48,"p":2,"text":"Carmelo Pacheco made Three Point Jumper. Assisted by Themus Fulks."},{"t":413,"wp":100.0,"hs":79,"as":49,"p":2,"text":"Anquan Boldin Jr made Free Throw."},{"t":398,"wp":100.0,"hs":81,"as":49,"p":2,"text":"George Beale Jr. made Layup."},{"t":375,"wp":100.0,"hs":81,"as":51,"p":2,"text":"Jaquan Sanders made Jumper. Assisted by Anquan Boldin Jr."},{"t":375,"wp":100.0,"hs":81,"as":52,"p":2,"text":"Jaquan Sanders made Free Throw."},{"t":360,"wp":100.0,"hs":84,"as":52,"p":2,"text":"George Beale Jr. made Three Point Jumper. Assisted by Elijah Hulsewe."},{"t":322,"wp":100.0,"hs":84,"as":53,"p":2,"text":"Devere Palmer Jr made Free Throw."},{"t":305,"wp":100.0,"hs":86,"as":53,"p":2,"text":"Riley Kugel made Jumper."},{"t":286,"wp":100.0,"hs":88,"as":53,"p":2,"text":"Devan Cambridge made Layup. Assisted by Riley Kugel."},{"t":188,"wp":100.0,"hs":90,"as":53,"p":2,"text":"George Beale Jr. made Layup."},{"t":144,"wp":100.0,"hs":90,"as":55,"p":2,"text":"Amir Rahman made Layup. Assisted by Malcolm Stute."},{"t":131,"wp":100.0,"hs":92,"as":55,"p":2,"text":"John Bol made Layup. Assisted by Chris Johnson."},{"t":131,"wp":100.0,"hs":93,"as":55,"p":2,"text":"John Bol made Free Throw."},{"t":88,"wp":100.0,"hs":93,"as":57,"p":2,"text":"Amir Rahman made Layup. Assisted by Kaleb Washington."},{"t":75,"wp":100.0,"hs":95,"as":57,"p":2,"text":"Poohpha Warakulnukroh made Jumper."},{"t":57,"wp":100.0,"hs":95,"as":60,"p":2,"text":"Anthony Knowles made Three Point Jumper. Assisted by Malcolm Stute."},{"t":35,"wp":100.0,"hs":97,"as":60,"p":2,"text":"John Bol made Layup."},{"t":0,"wp":100.0,"hs":97,"as":60,"p":2,"text":"End of 2nd half"},{"t":0,"wp":100.0,"hs":97,"as":60,"p":2,"text":"End of Game"},{"t":0,"wp":100.0,"hs":97,"as":60,"p":2,"text":"Final"}],"runs":[{"team":"UCF","run":"12-0","pts":12,"period":1,"start_clock":"16:35","end_clock":"12:59","start_score":"7-3","end_score":"19-3"}],"lead_changes":0,"ties":4,"largest_lead":{"home":38,"away":0},"big_swings":[{"idx":4,"swing":2.4,"text":"Jamichael Stillwell made Three Point Jumper. Assisted by Themus Fulks.","wp":92.4},{"idx":6,"swing":2.1,"text":"Riley Kugel made Three Point Jumper. Assisted by Jamichael Stillwell.","wp":94.0},{"idx":3,"swing":1.9,"text":"John Bol made Jumper. Assisted by Themus Fulks.","wp":90.0},{"idx":1,"swing":1.7,"text":"Themus Fulks made Jumper. Assisted by Jordan Burks.","wp":89.6},{"idx":2,"swing":1.5,"text":"Antonio Baker Jr. made Jumper.","wp":88.1}]}