{"game_id":"401856534","date":"2026-03-21","n_ot":0,"home":{"abbr":"NEB","name":"Nebraska Cornhuskers","score":74,"players":[{"id":"4897432","name":"Sam Hoiberg","starter":true,"dnp":false,"min":38,"ortg":101.5,"pts":8,"fg":"3-6","3pt":"0-0","ft":"2-2","reb":4,"oreb":1,"dreb":3,"ast":6,"stl":1,"blk":0,"to":1,"pf":3},{"id":"4858604","name":"Pryce Sandfort","starter":true,"dnp":false,"min":37,"ortg":132.5,"pts":15,"fg":"5-9","3pt":"3-6","ft":"2-3","reb":5,"oreb":0,"dreb":5,"ast":2,"stl":1,"blk":0,"to":1,"pf":3},{"id":"4592677","name":"Rienk Mast","starter":true,"dnp":false,"min":34,"ortg":130.0,"pts":13,"fg":"5-10","3pt":"3-6","ft":"0-0","reb":5,"oreb":1,"dreb":4,"ast":4,"stl":0,"blk":0,"to":0,"pf":3},{"id":"5174982","name":"Berke Buyuktuncel","starter":true,"dnp":false,"min":27,"ortg":186.3,"pts":12,"fg":"5-6","3pt":"2-2","ft":"0-1","reb":4,"oreb":0,"dreb":4,"ast":1,"stl":0,"blk":0,"to":0,"pf":2},{"id":"5105825","name":"Jamarques Lawrence","starter":true,"dnp":false,"min":20,"ortg":106.6,"pts":9,"fg":"4-6","3pt":"0-1","ft":"1-1","reb":1,"oreb":0,"dreb":1,"ast":1,"stl":2,"blk":0,"to":2,"pf":4},{"id":"5239571","name":"Braden Frager","starter":false,"dnp":false,"min":28,"ortg":97.9,"pts":15,"fg":"6-11","3pt":"1-3","ft":"2-3","reb":5,"oreb":0,"dreb":5,"ast":2,"stl":1,"blk":0,"to":3,"pf":2},{"id":"5105827","name":"Cale Jacobsen","starter":false,"dnp":false,"min":14,"ortg":0.0,"pts":0,"fg":"0-3","3pt":"0-1","ft":"0-0","reb":2,"oreb":0,"dreb":2,"ast":0,"stl":0,"blk":0,"to":3,"pf":1},{"id":"5263670","name":"Leo Curtis","starter":false,"dnp":false,"min":2,"ortg":200.0,"pts":2,"fg":"1-1","3pt":"0-0","ft":"0-0","reb":0,"oreb":0,"dreb":0,"ast":0,"stl":0,"blk":0,"to":0,"pf":0},{"id":"5248172","name":"Will Cooper","starter":false,"dnp":true,"min":0,"ortg":null,"pts":0,"fg":"","3pt":"","ft":"","reb":0,"oreb":0,"dreb":0,"ast":0,"stl":0,"blk":0,"to":0,"pf":0},{"id":"5239573","name":"Justin Bolis","starter":false,"dnp":true,"min":0,"ortg":null,"pts":0,"fg":"","3pt":"","ft":"","reb":0,"oreb":0,"dreb":0,"ast":0,"stl":0,"blk":0,"to":0,"pf":0},{"id":"5108721","name":"Ugnius Jarusevicius","starter":false,"dnp":true,"min":0,"ortg":null,"pts":0,"fg":"","3pt":"","ft":"","reb":0,"oreb":0,"dreb":0,"ast":0,"stl":0,"blk":0,"to":0,"pf":0},{"id":"5105828","name":"Henry Burt","starter":false,"dnp":true,"min":0,"ortg":null,"pts":0,"fg":"","3pt":"","ft":"","reb":0,"oreb":0,"dreb":0,"ast":0,"stl":0,"blk":0,"to":0,"pf":0},{"id":"4702740","name":"Jared Garcia","starter":false,"dnp":true,"min":0,"ortg":null,"pts":0,"fg":"","3pt":"","ft":"","reb":0,"oreb":0,"dreb":0,"ast":0,"stl":0,"blk":0,"to":0,"pf":0},{"id":"5254162","name":"Quentin Rhymes","starter":false,"dnp":true,"min":0,"ortg":null,"pts":0,"fg":"","3pt":"","ft":"","reb":0,"oreb":0,"dreb":0,"ast":0,"stl":0,"blk":0,"to":0,"pf":0},{"id":"5109018","name":"Kendall Blue","starter":false,"dnp":true,"min":0,"ortg":null,"pts":0,"fg":"","3pt":"","ft":"","reb":0,"oreb":0,"dreb":0,"ast":0,"stl":0,"blk":0,"to":0,"pf":0},{"id":"5105861","name":"Connor Essegian","starter":false,"dnp":true,"min":0,"ortg":null,"pts":0,"fg":"","3pt":"","ft":"","reb":0,"oreb":0,"dreb":0,"ast":0,"stl":0,"blk":0,"to":0,"pf":0}],"totals":{"min":200,"pts":74,"reb":26,"oreb":2,"dreb":24,"ast":16,"stl":5,"blk":0,"to":10,"pf":18,"fgm":29,"fga":52,"tpm":9,"tpa":19,"ftm":7,"fta":10,"fg":"29-52","3pt":"9-19","ft":"7-10","fg_pct":55.8,"3pt_pct":47.4,"ft_pct":70.0,"opp_dreb":18},"four_factors":{"efg_pct":64.4,"to_pct":15.1,"or_pct":10.0,"ftr":19.2},"wab":0.768,"adj_oe":116.1,"adj_de":112.5},"away":{"abbr":"VAN","name":"Vanderbilt Commodores","score":72,"players":[{"id":"5187600","name":"Tyler Tanner","starter":true,"dnp":false,"min":38,"ortg":108.2,"pts":27,"fg":"9-21","3pt":"3-10","ft":"6-9","reb":2,"oreb":0,"dreb":2,"ast":4,"stl":4,"blk":0,"to":0,"pf":1},{"id":"4838721","name":"Tyler Nickel","starter":true,"dnp":false,"min":33,"ortg":107.5,"pts":16,"fg":"5-13","3pt":"5-12","ft":"1-2","reb":5,"oreb":1,"dreb":4,"ast":1,"stl":1,"blk":0,"to":1,"pf":3},{"id":"5114350","name":"AK Okereke","starter":true,"dnp":false,"min":32,"ortg":128.6,"pts":9,"fg":"3-7","3pt":"3-5","ft":"0-0","reb":7,"oreb":3,"dreb":4,"ast":1,"stl":0,"blk":2,"to":0,"pf":3},{"id":"4702049","name":"Duke Miles","starter":true,"dnp":false,"min":32,"ortg":57.1,"pts":9,"fg":"2-10","3pt":"1-8","ft":"4-4","reb":0,"oreb":0,"dreb":0,"ast":6,"stl":1,"blk":0,"to":4,"pf":2},{"id":"4791227","name":"Devin McGlockton","starter":true,"dnp":false,"min":29,"ortg":63.0,"pts":3,"fg":"1-2","3pt":"1-2","ft":"0-4","reb":8,"oreb":3,"dreb":5,"ast":0,"stl":0,"blk":0,"to":1,"pf":2},{"id":"5311759","name":"Chandler Bing","starter":false,"dnp":false,"min":22,"ortg":66.7,"pts":2,"fg":"1-2","3pt":"0-0","ft":"0-0","reb":2,"oreb":1,"dreb":1,"ast":3,"stl":0,"blk":1,"to":1,"pf":3},{"id":"4433625","name":"Jalen Washington","starter":false,"dnp":false,"min":14,"ortg":150.0,"pts":6,"fg":"3-3","3pt":"0-0","ft":"0-0","reb":5,"oreb":3,"dreb":2,"ast":0,"stl":0,"blk":1,"to":1,"pf":2},{"id":"5176497","name":"Tyler Harris","starter":false,"dnp":true,"min":0,"ortg":null,"pts":0,"fg":"","3pt":"","ft":"","reb":0,"oreb":0,"dreb":0,"ast":0,"stl":0,"blk":0,"to":0,"pf":0},{"id":"5106670","name":"Mason Nicholson","starter":false,"dnp":true,"min":0,"ortg":null,"pts":0,"fg":"","3pt":"","ft":"","reb":0,"oreb":0,"dreb":0,"ast":0,"stl":0,"blk":0,"to":0,"pf":0},{"id":"5254169","name":"Jayden Leverett","starter":false,"dnp":true,"min":0,"ortg":null,"pts":0,"fg":"","3pt":"","ft":"","reb":0,"oreb":0,"dreb":0,"ast":0,"stl":0,"blk":0,"to":0,"pf":0},{"id":"5239784","name":"George Kimble III","starter":false,"dnp":true,"min":0,"ortg":null,"pts":0,"fg":"","3pt":"","ft":"","reb":0,"oreb":0,"dreb":0,"ast":0,"stl":0,"blk":0,"to":0,"pf":0},{"id":"5221327","name":"Jaylon Dean-Vines","starter":false,"dnp":true,"min":0,"ortg":null,"pts":0,"fg":"","3pt":"","ft":"","reb":0,"oreb":0,"dreb":0,"ast":0,"stl":0,"blk":0,"to":0,"pf":0},{"id":"5174287","name":"Coleson Messer","starter":false,"dnp":true,"min":0,"ortg":null,"pts":0,"fg":"","3pt":"","ft":"","reb":0,"oreb":0,"dreb":0,"ast":0,"stl":0,"blk":0,"to":0,"pf":0},{"id":"5105281","name":"Miles Keeffe","starter":false,"dnp":true,"min":0,"ortg":null,"pts":0,"fg":"","3pt":"","ft":"","reb":0,"oreb":0,"dreb":0,"ast":0,"stl":0,"blk":0,"to":0,"pf":0},{"id":"4684164","name":"Mike James","starter":false,"dnp":true,"min":0,"ortg":null,"pts":0,"fg":"","3pt":"","ft":"","reb":0,"oreb":0,"dreb":0,"ast":0,"stl":0,"blk":0,"to":0,"pf":0},{"id":"4433616","name":"Frankie Collins","starter":false,"dnp":true,"min":0,"ortg":null,"pts":0,"fg":"","3pt":"","ft":"","reb":0,"oreb":0,"dreb":0,"ast":0,"stl":0,"blk":0,"to":0,"pf":0}],"totals":{"min":200,"pts":72,"reb":29,"oreb":11,"dreb":18,"ast":15,"stl":6,"blk":4,"to":8,"pf":16,"fgm":24,"fga":58,"tpm":13,"tpa":37,"ftm":11,"fta":19,"fg":"24-58","3pt":"13-37","ft":"11-19","fg_pct":41.4,"3pt_pct":35.1,"ft_pct":57.9,"opp_dreb":24},"four_factors":{"efg_pct":52.6,"to_pct":10.8,"or_pct":31.4,"ftr":32.8},"wab":-0.231,"adj_oe":112.5,"adj_de":116.1},"tempo":63.8,"poss":63.8,"spread":1.5,"wp":[{"t":2400,"wp":53.4,"hs":0,"as":0,"p":1,"text":"Game Start"},{"t":2354,"wp":59.9,"hs":3,"as":0,"p":1,"text":"Berke Buyuktuncel makes 23-foot three point jumper (Sam Hoiberg assists)"},{"t":2312,"wp":64.1,"hs":5,"as":0,"p":1,"text":"Jamarques Lawrence makes layup (Sam Hoiberg assists)"},{"t":2273,"wp":70.0,"hs":8,"as":0,"p":1,"text":"Rienk Mast makes 23-foot three point jumper"},{"t":2249,"wp":66.5,"hs":8,"as":2,"p":1,"text":"Tyler Tanner makes 10-foot floating jump shot"},{"t":2166,"wp":72.9,"hs":11,"as":2,"p":1,"text":"Rienk Mast makes 26-foot three point jumper (Sam Hoiberg assists)"},{"t":2143,"wp":69.4,"hs":11,"as":4,"p":1,"text":"Tyler Tanner makes driving layup"},{"t":2097,"wp":73.7,"hs":13,"as":4,"p":1,"text":"Jamarques Lawrence makes layup (Rienk Mast assists)"},{"t":2097,"wp":75.4,"hs":14,"as":4,"p":1,"text":"Jamarques Lawrence makes free throw 1 of 1"},{"t":2077,"wp":72.1,"hs":14,"as":6,"p":1,"text":"Jalen Washington makes layup (Tyler Tanner assists)"},{"t":2035,"wp":70.5,"hs":14,"as":7,"p":1,"text":"Tyler Tanner makes free throw 1 of 2"},{"t":2035,"wp":68.5,"hs":14,"as":8,"p":1,"text":"Tyler Tanner makes free throw 2 of 2"},{"t":1936,"wp":64.7,"hs":14,"as":10,"p":1,"text":"Tyler Tanner makes 5-foot dunk"},{"t":1885,"wp":70.0,"hs":16,"as":10,"p":1,"text":"Braden Frager makes driving layup (Pryce Sandfort assists)"},{"t":1815,"wp":75.2,"hs":18,"as":10,"p":1,"text":"Braden Frager makes layup (Sam Hoiberg assists)"},{"t":1785,"wp":73.4,"hs":18,"as":11,"p":1,"text":"Duke Miles makes free throw 1 of 2"},{"t":1785,"wp":71.0,"hs":18,"as":12,"p":1,"text":"Duke Miles makes free throw 2 of 2"},{"t":1732,"wp":63.5,"hs":18,"as":15,"p":1,"text":"Tyler Tanner makes 26-foot three point jumper (Tyler Nickel assists)"},{"t":1718,"wp":71.8,"hs":21,"as":15,"p":1,"text":"Rienk Mast makes 28-foot three point jumper (Sam Hoiberg assists)"},{"t":1680,"wp":66.8,"hs":21,"as":17,"p":1,"text":"Jalen Washington makes 3-foot dunk (Tyler Tanner assists)"},{"t":1605,"wp":73.1,"hs":23,"as":17,"p":1,"text":"Braden Frager makes layup (Rienk Mast assists)"},{"t":1582,"wp":67.7,"hs":23,"as":19,"p":1,"text":"Jalen Washington makes 1-foot dunk (Chandler Bing assists)"},{"t":1552,"wp":73.7,"hs":25,"as":19,"p":1,"text":"Berke Buyuktuncel makes layup"},{"t":1507,"wp":79.3,"hs":27,"as":19,"p":1,"text":"Pryce Sandfort makes 11-foot turnaround jump shot"},{"t":1473,"wp":74.7,"hs":27,"as":21,"p":1,"text":"Tyler Tanner makes 2-foot dunk"},{"t":1461,"wp":77.5,"hs":28,"as":21,"p":1,"text":"Sam Hoiberg makes free throw 1 of 2"},{"t":1461,"wp":80.0,"hs":29,"as":21,"p":1,"text":"Sam Hoiberg makes free throw 2 of 2"},{"t":1439,"wp":84.6,"hs":31,"as":21,"p":1,"text":"Braden Frager makes driving layup"},{"t":1425,"wp":78.0,"hs":31,"as":24,"p":1,"text":"AK Okereke makes 27-foot three point jumper (Chandler Bing assists)"},{"t":1405,"wp":75.6,"hs":31,"as":25,"p":1,"text":"Tyler Tanner makes free throw 1 of 2"},{"t":1405,"wp":72.7,"hs":31,"as":26,"p":1,"text":"Tyler Tanner makes free throw 2 of 2"},{"t":1383,"wp":81.1,"hs":34,"as":26,"p":1,"text":"Pryce Sandfort makes 25-foot three pointer"},{"t":1364,"wp":78.9,"hs":34,"as":27,"p":1,"text":"Duke Miles makes free throw 1 of 2"},{"t":1364,"wp":76.1,"hs":34,"as":28,"p":1,"text":"Duke Miles makes free throw 2 of 2"},{"t":1339,"wp":73.5,"hs":34,"as":29,"p":1,"text":"Tyler Nickel makes free throw 1 of 2"},{"t":1295,"wp":79.9,"hs":36,"as":29,"p":1,"text":"Leo Curtis makes 1-foot dunk (Braden Frager assists)"},{"t":1267,"wp":71.0,"hs":36,"as":32,"p":1,"text":"Tyler Nickel makes 27-foot three point jumper (Duke Miles assists)"},{"t":1251,"wp":80.6,"hs":39,"as":32,"p":1,"text":"Pryce Sandfort makes 24-foot three pointer"},{"t":1200,"wp":81.3,"hs":39,"as":32,"p":1,"text":"End of 1st half"},{"t":1191,"wp":78.6,"hs":39,"as":33,"p":2,"text":"Tyler Tanner makes free throw 2 of 2"},{"t":1167,"wp":68.2,"hs":39,"as":36,"p":2,"text":"Tyler Nickel makes 23-foot three point jumper (Duke Miles assists)"},{"t":1145,"wp":76.0,"hs":41,"as":36,"p":2,"text":"Sam Hoiberg makes driving layup"},{"t":1010,"wp":84.3,"hs":43,"as":36,"p":2,"text":"Jamarques Lawrence makes 2-foot dunk"},{"t":996,"wp":78.1,"hs":43,"as":38,"p":2,"text":"Duke Miles makes 9-foot pullup jump shot"},{"t":977,"wp":84.9,"hs":45,"as":38,"p":2,"text":"Jamarques Lawrence makes layup (Rienk Mast assists)"},{"t":961,"wp":74.8,"hs":45,"as":41,"p":2,"text":"Tyler Nickel makes 24-foot three point jumper (Duke Miles assists)"},{"t":931,"wp":85.7,"hs":48,"as":41,"p":2,"text":"Berke Buyuktuncel makes 23-foot three point jumper (Jamarques Lawrence assists)"},{"t":913,"wp":75.4,"hs":48,"as":44,"p":2,"text":"Duke Miles makes 23-foot three pointer"},{"t":829,"wp":84.3,"hs":50,"as":44,"p":2,"text":"Sam Hoiberg makes layup"},{"t":813,"wp":72.2,"hs":50,"as":47,"p":2,"text":"Tyler Nickel makes 24-foot three point jumper (Tyler Tanner assists)"},{"t":700,"wp":61.3,"hs":50,"as":49,"p":2,"text":"Chandler Bing makes layup"},{"t":646,"wp":79.7,"hs":53,"as":49,"p":2,"text":"Pryce Sandfort makes 24-foot three point jumper (Braden Frager assists)"},{"t":619,"wp":61.8,"hs":53,"as":52,"p":2,"text":"Tyler Tanner makes 23-foot three point jumper (AK Okereke assists)"},{"t":607,"wp":69.0,"hs":54,"as":52,"p":2,"text":"Braden Frager makes free throw 1 of 2"},{"t":607,"wp":75.2,"hs":55,"as":52,"p":2,"text":"Braden Frager makes free throw 2 of 2"},{"t":589,"wp":69.3,"hs":55,"as":53,"p":2,"text":"Tyler Tanner makes free throw 2 of 2"},{"t":545,"wp":53.4,"hs":55,"as":55,"p":2,"text":"Tyler Tanner makes driving layup"},{"t":506,"wp":27.0,"hs":55,"as":58,"p":2,"text":"AK Okereke makes 25-foot three point jumper (Duke Miles assists)"},{"t":480,"wp":42.8,"hs":57,"as":58,"p":2,"text":"Rienk Mast makes driving layup"},{"t":458,"wp":19.4,"hs":57,"as":61,"p":2,"text":"Devin McGlockton makes 23-foot three point jumper (Chandler Bing assists)"},{"t":434,"wp":42.1,"hs":60,"as":61,"p":2,"text":"Braden Frager makes 23-foot three point jumper (Sam Hoiberg assists)"},{"t":406,"wp":17.7,"hs":60,"as":64,"p":2,"text":"Tyler Tanner makes 23-foot three point jumper (Duke Miles assists)"},{"t":386,"wp":31.5,"hs":62,"as":64,"p":2,"text":"Berke Buyuktuncel makes driving layup"},{"t":334,"wp":10.2,"hs":62,"as":67,"p":2,"text":"Tyler Nickel makes 26-foot three point jumper (Tyler Tanner assists)"},{"t":311,"wp":20.7,"hs":64,"as":67,"p":2,"text":"Pryce Sandfort makes 7-foot pullup jump shot"},{"t":218,"wp":25.2,"hs":65,"as":67,"p":2,"text":"Pryce Sandfort makes free throw 1 of 2"},{"t":218,"wp":37.0,"hs":66,"as":67,"p":2,"text":"Pryce Sandfort makes free throw 2 of 2"},{"t":128,"wp":70.0,"hs":68,"as":67,"p":2,"text":"Berke Buyuktuncel makes layup (Rienk Mast assists)"},{"t":104,"wp":16.6,"hs":68,"as":70,"p":2,"text":"AK Okereke makes 23-foot three point jumper (Duke Miles assists)"},{"t":80,"wp":51.4,"hs":70,"as":70,"p":2,"text":"Sam Hoiberg makes layup"},{"t":58,"wp":10.1,"hs":70,"as":72,"p":2,"text":"Tyler Tanner makes driving layup"},{"t":37,"wp":51.0,"hs":72,"as":72,"p":2,"text":"Rienk Mast makes 0-foot tip in layup"},{"t":2,"wp":100.0,"hs":74,"as":72,"p":2,"text":"Braden Frager makes layup (Pryce Sandfort assists)"},{"t":0,"wp":100.0,"hs":74,"as":72,"p":2,"text":"End of 2nd half"},{"t":0,"wp":100.0,"hs":74,"as":72,"p":2,"text":"End of Game"},{"t":0,"wp":100.0,"hs":74,"as":72,"p":2,"text":"Final"}],"runs":[],"lead_changes":4,"ties":14,"largest_lead":{"home":10,"away":5},"big_swings":[{"idx":68,"swing":53.4,"text":"AK Okereke makes 23-foot three point jumper (Duke Miles assists)","wp":16.6},{"idx":72,"swing":49.0,"text":"Braden Frager makes layup (Pryce Sandfort assists)","wp":100.0},{"idx":70,"swing":41.3,"text":"Tyler Tanner makes driving layup","wp":10.1},{"idx":71,"swing":40.9,"text":"Rienk Mast makes 0-foot tip in layup","wp":51.0},{"idx":69,"swing":34.8,"text":"Sam Hoiberg makes layup","wp":51.4}]}