{"game_id":"401828192","date":"2026-01-24","n_ot":0,"home":{"abbr":"WICH","name":"Wichita State Shockers","score":74,"players":[{"id":"5107508","name":"Kenyon Giles","starter":true,"dnp":false,"min":40,"ortg":82.4,"pts":14,"fg":"6-16","3pt":"2-8","ft":"0-0","reb":3,"oreb":1,"dreb":2,"ast":3,"stl":2,"blk":0,"to":1,"pf":1},{"id":"4710354","name":"Michael Gray Jr.","starter":true,"dnp":false,"min":30,"ortg":37.5,"pts":3,"fg":"1-5","3pt":"1-4","ft":"0-0","reb":5,"oreb":0,"dreb":5,"ast":3,"stl":0,"blk":0,"to":3,"pf":3},{"id":"5181250","name":"Dillon Battie","starter":true,"dnp":false,"min":24,"ortg":87.4,"pts":13,"fg":"6-11","3pt":"1-3","ft":"0-2","reb":8,"oreb":3,"dreb":5,"ast":3,"stl":2,"blk":1,"to":3,"pf":2},{"id":"5176140","name":"Karon Boyd","starter":true,"dnp":false,"min":23,"ortg":93.3,"pts":14,"fg":"6-14","3pt":"2-6","ft":"0-0","reb":1,"oreb":1,"dreb":0,"ast":0,"stl":0,"blk":1,"to":1,"pf":2},{"id":"5125176","name":"Emmanuel Okorafor","starter":true,"dnp":false,"min":16,"ortg":120.0,"pts":6,"fg":"3-5","3pt":"0-0","ft":"0-0","reb":4,"oreb":0,"dreb":4,"ast":0,"stl":1,"blk":1,"to":0,"pf":1},{"id":"5105857","name":"Will Berg","starter":false,"dnp":false,"min":24,"ortg":101.2,"pts":10,"fg":"4-6","3pt":"0-0","ft":"2-2","reb":10,"oreb":4,"dreb":6,"ast":4,"stl":1,"blk":0,"to":3,"pf":2},{"id":"4873115","name":"TJ Williams","starter":false,"dnp":false,"min":17,"ortg":25.8,"pts":1,"fg":"0-3","3pt":"0-0","ft":"1-2","reb":2,"oreb":1,"dreb":1,"ast":3,"stl":1,"blk":0,"to":0,"pf":2},{"id":"5313656","name":"Dre Kindell","starter":false,"dnp":false,"min":13,"ortg":103.1,"pts":4,"fg":"1-2","3pt":"0-0","ft":"2-2","reb":2,"oreb":0,"dreb":2,"ast":0,"stl":0,"blk":0,"to":1,"pf":3},{"id":"5241241","name":"Brian Amuneke","starter":false,"dnp":false,"min":13,"ortg":180.0,"pts":9,"fg":"3-5","3pt":"3-5","ft":"0-0","reb":1,"oreb":0,"dreb":1,"ast":1,"stl":0,"blk":0,"to":0,"pf":2},{"id":"5313658","name":"Noah Hill","starter":false,"dnp":true,"min":0,"ortg":null,"pts":0,"fg":"","3pt":"","ft":"","reb":0,"oreb":0,"dreb":0,"ast":0,"stl":0,"blk":0,"to":0,"pf":0},{"id":"5106701","name":"Jaret Valencia","starter":false,"dnp":true,"min":0,"ortg":null,"pts":0,"fg":"","3pt":"","ft":"","reb":0,"oreb":0,"dreb":0,"ast":0,"stl":0,"blk":0,"to":0,"pf":0},{"id":"5106651","name":"Henry Thengvall","starter":false,"dnp":true,"min":0,"ortg":null,"pts":0,"fg":"","3pt":"","ft":"","reb":0,"oreb":0,"dreb":0,"ast":0,"stl":0,"blk":0,"to":0,"pf":0},{"id":"5313657","name":"Pierre Couisnard","starter":false,"dnp":true,"min":0,"ortg":null,"pts":0,"fg":"","3pt":"","ft":"","reb":0,"oreb":0,"dreb":0,"ast":0,"stl":0,"blk":0,"to":0,"pf":0},{"id":"5254177","name":"Tyrus Rathan-Mayes","starter":false,"dnp":true,"min":0,"ortg":null,"pts":0,"fg":"","3pt":"","ft":"","reb":0,"oreb":0,"dreb":0,"ast":0,"stl":0,"blk":0,"to":0,"pf":0},{"id":"5175746","name":"Joy Ighovodja","starter":false,"dnp":true,"min":0,"ortg":null,"pts":0,"fg":"","3pt":"","ft":"","reb":0,"oreb":0,"dreb":0,"ast":0,"stl":0,"blk":0,"to":0,"pf":0}],"totals":{"min":200,"pts":74,"reb":36,"oreb":10,"dreb":26,"ast":17,"stl":7,"blk":3,"to":12,"pf":18,"fgm":30,"fga":67,"tpm":9,"tpa":26,"ftm":5,"fta":8,"fg":"30-67","3pt":"9-26","ft":"5-8","fg_pct":44.8,"3pt_pct":34.6,"ft_pct":62.5,"opp_dreb":27},"four_factors":{"efg_pct":51.5,"to_pct":14.5,"or_pct":27.0,"ftr":11.9},"wab":0.128,"adj_oe":101.5,"adj_de":83.3},"away":{"abbr":"MEM","name":"Memphis Tigers","score":59,"players":[{"id":"5037872","name":"Curtis Givens III","starter":true,"dnp":false,"min":25,"ortg":93.5,"pts":11,"fg":"4-9","3pt":"1-4","ft":"2-4","reb":0,"oreb":0,"dreb":0,"ast":2,"stl":0,"blk":0,"to":1,"pf":1},{"id":"4685683","name":"Aaron Bradshaw","starter":true,"dnp":false,"min":24,"ortg":100.0,"pts":10,"fg":"5-9","3pt":"0-3","ft":"0-0","reb":9,"oreb":1,"dreb":8,"ast":0,"stl":2,"blk":0,"to":1,"pf":3},{"id":"5105618","name":"Quante Berry","starter":true,"dnp":false,"min":24,"ortg":75.0,"pts":3,"fg":"1-4","3pt":"1-3","ft":"0-0","reb":1,"oreb":0,"dreb":1,"ast":1,"stl":1,"blk":1,"to":0,"pf":1},{"id":"5105805","name":"Dug McDaniel","starter":true,"dnp":false,"min":22,"ortg":45.0,"pts":4,"fg":"1-5","3pt":"0-1","ft":"2-2","reb":2,"oreb":0,"dreb":2,"ast":3,"stl":1,"blk":0,"to":3,"pf":0},{"id":"5176660","name":"Hasan Abdul Hakim","starter":true,"dnp":false,"min":13,"ortg":28.6,"pts":2,"fg":"1-3","3pt":"0-0","ft":"0-0","reb":4,"oreb":1,"dreb":3,"ast":0,"stl":0,"blk":0,"to":4,"pf":1},{"id":"5242617","name":"Julius Thedford","starter":false,"dnp":false,"min":24,"ortg":74.2,"pts":7,"fg":"3-8","3pt":"0-1","ft":"1-1","reb":6,"oreb":2,"dreb":4,"ast":1,"stl":1,"blk":0,"to":1,"pf":4},{"id":"5105548","name":"Zach Davis","starter":false,"dnp":false,"min":20,"ortg":66.7,"pts":6,"fg":"3-7","3pt":"0-1","ft":"0-0","reb":4,"oreb":0,"dreb":4,"ast":1,"stl":2,"blk":1,"to":2,"pf":1},{"id":"5313374","name":"Simon Majok","starter":false,"dnp":false,"min":17,"ortg":120.2,"pts":10,"fg":"4-5","3pt":"0-0","ft":"2-3","reb":3,"oreb":2,"dreb":1,"ast":0,"stl":2,"blk":0,"to":2,"pf":1},{"id":"4711280","name":"Ashton Hardaway","starter":false,"dnp":false,"min":15,"ortg":71.1,"pts":6,"fg":"2-7","3pt":"1-5","ft":"1-1","reb":2,"oreb":0,"dreb":2,"ast":0,"stl":0,"blk":0,"to":1,"pf":1},{"id":"4431995","name":"Tariq Ingraham","starter":false,"dnp":false,"min":6,"ortg":0.0,"pts":0,"fg":"0-0","3pt":"0-0","ft":"0-0","reb":2,"oreb":0,"dreb":2,"ast":0,"stl":0,"blk":1,"to":1,"pf":0},{"id":"5106647","name":"Thierno Sylla","starter":false,"dnp":false,"min":6,"ortg":0.0,"pts":0,"fg":"0-2","3pt":"0-1","ft":"0-0","reb":0,"oreb":0,"dreb":0,"ast":0,"stl":0,"blk":0,"to":0,"pf":1},{"id":"5177047","name":"William Whorton","starter":false,"dnp":false,"min":4,"ortg":0.0,"pts":0,"fg":"0-0","3pt":"0-0","ft":"0-0","reb":0,"oreb":0,"dreb":0,"ast":0,"stl":0,"blk":0,"to":1,"pf":1},{"id":"5180726","name":"Mason Matthews","starter":false,"dnp":true,"min":0,"ortg":null,"pts":0,"fg":"","3pt":"","ft":"","reb":0,"oreb":0,"dreb":0,"ast":0,"stl":0,"blk":0,"to":0,"pf":0},{"id":"5175888","name":"Arop Arop","starter":false,"dnp":true,"min":0,"ortg":null,"pts":0,"fg":"","3pt":"","ft":"","reb":0,"oreb":0,"dreb":0,"ast":0,"stl":0,"blk":0,"to":0,"pf":0},{"id":"5105984","name":"Sincere Parker","starter":false,"dnp":true,"min":0,"ortg":null,"pts":0,"fg":"","3pt":"","ft":"","reb":0,"oreb":0,"dreb":0,"ast":0,"stl":0,"blk":0,"to":0,"pf":0}],"totals":{"min":200,"pts":59,"reb":33,"oreb":6,"dreb":27,"ast":8,"stl":9,"blk":3,"to":17,"pf":15,"fgm":24,"fga":59,"tpm":3,"tpa":19,"ftm":8,"fta":11,"fg":"24-59","3pt":"3-19","ft":"8-11","fg_pct":40.7,"3pt_pct":15.8,"ft_pct":72.7,"opp_dreb":26},"four_factors":{"efg_pct":43.2,"to_pct":21.0,"or_pct":18.8,"ftr":18.6},"wab":-0.615,"adj_oe":83.3,"adj_de":101.5},"tempo":71.8,"poss":71.8,"spread":6.8,"wp":[{"t":2400,"wp":64.0,"hs":0,"as":0,"p":1,"text":"Game Start"},{"t":2341,"wp":60.3,"hs":0,"as":2,"p":1,"text":"Hasan Abdul Hakim makes 5-foot jumper"},{"t":2309,"wp":58.2,"hs":0,"as":3,"p":1,"text":"Dug McDaniel makes free throw 1 of 2"},{"t":2309,"wp":56.0,"hs":0,"as":4,"p":1,"text":"Dug McDaniel makes free throw 2 of 2"},{"t":2247,"wp":60.3,"hs":2,"as":4,"p":1,"text":"Kenyon Giles makes 17-foot pullup jump shot"},{"t":2231,"wp":64.6,"hs":4,"as":4,"p":1,"text":"Dillon Battie makes driving layup"},{"t":2197,"wp":70.5,"hs":7,"as":4,"p":1,"text":"Michael Gray Jr. makes 27-foot three point jumper (Kenyon Giles assists)"},{"t":2147,"wp":74.4,"hs":9,"as":4,"p":1,"text":"Karon Boyd makes layup"},{"t":2086,"wp":78.2,"hs":11,"as":4,"p":1,"text":"Dillon Battie makes layup"},{"t":2020,"wp":80.4,"hs":12,"as":4,"p":1,"text":"TJ Williams makes free throw 1 of 2"},{"t":2002,"wp":77.4,"hs":12,"as":6,"p":1,"text":"Julius Thedford makes driving layup"},{"t":1988,"wp":80.8,"hs":14,"as":6,"p":1,"text":"Will Berg makes 0-foot tip in layup"},{"t":1948,"wp":84.2,"hs":16,"as":6,"p":1,"text":"Kenyon Giles makes 15-foot pullup jump shot"},{"t":1880,"wp":88.7,"hs":19,"as":6,"p":1,"text":"Brian Amuneke makes 26-foot three point jumper (TJ Williams assists)"},{"t":1851,"wp":86.6,"hs":19,"as":8,"p":1,"text":"Julius Thedford makes 0-foot tip in layup"},{"t":1694,"wp":91.9,"hs":22,"as":8,"p":1,"text":"Brian Amuneke makes 24-foot three point jumper (Kenyon Giles assists)"},{"t":1632,"wp":94.4,"hs":24,"as":8,"p":1,"text":"Dillon Battie makes 2-foot dunk (Michael Gray Jr. assists)"},{"t":1592,"wp":96.1,"hs":26,"as":8,"p":1,"text":"Emmanuel Okorafor makes 2-foot dunk (Brian Amuneke assists)"},{"t":1546,"wp":97.9,"hs":29,"as":8,"p":1,"text":"Brian Amuneke makes 25-foot three point jumper (Dillon Battie assists)"},{"t":1525,"wp":96.7,"hs":29,"as":11,"p":1,"text":"Ashton Hardaway makes 25-foot three point jumper (Dug McDaniel assists)"},{"t":1503,"wp":97.8,"hs":31,"as":11,"p":1,"text":"Dillon Battie makes 1-foot dunk (Will Berg assists)"},{"t":1482,"wp":97.0,"hs":31,"as":13,"p":1,"text":"Aaron Bradshaw makes 0-foot tip in layup"},{"t":1438,"wp":96.2,"hs":31,"as":15,"p":1,"text":"Dug McDaniel makes 18-foot pullup jump shot"},{"t":1420,"wp":94.8,"hs":31,"as":17,"p":1,"text":"Aaron Bradshaw makes 2-foot dunk (Dug McDaniel assists)"},{"t":1360,"wp":96.1,"hs":32,"as":17,"p":1,"text":"Will Berg makes free throw 1 of 2"},{"t":1360,"wp":96.8,"hs":33,"as":17,"p":1,"text":"Will Berg makes free throw 2 of 2"},{"t":1338,"wp":95.5,"hs":33,"as":19,"p":1,"text":"Aaron Bradshaw makes 16-foot jumper (Dug McDaniel assists)"},{"t":1312,"wp":97.1,"hs":35,"as":19,"p":1,"text":"Dillon Battie makes layup (Michael Gray Jr. assists)"},{"t":1285,"wp":96.0,"hs":35,"as":21,"p":1,"text":"Ashton Hardaway makes 7-foot pullup jump shot"},{"t":1285,"wp":95.2,"hs":35,"as":22,"p":1,"text":"Ashton Hardaway makes free throw 1 of 1"},{"t":1267,"wp":96.9,"hs":37,"as":22,"p":1,"text":"Will Berg makes layup"},{"t":1237,"wp":98.5,"hs":40,"as":22,"p":1,"text":"Kenyon Giles makes 24-foot three point jumper (Will Berg assists)"},{"t":1200,"wp":98.7,"hs":40,"as":22,"p":1,"text":"End of 1st half"},{"t":1183,"wp":99.3,"hs":42,"as":22,"p":2,"text":"Emmanuel Okorafor makes 1-foot dunk (Michael Gray Jr. assists)"},{"t":1103,"wp":99.7,"hs":44,"as":22,"p":2,"text":"Emmanuel Okorafor makes 1-foot dunk (Dillon Battie assists)"},{"t":1027,"wp":99.9,"hs":46,"as":22,"p":2,"text":"Kenyon Giles makes 6-foot floating jump shot"},{"t":1004,"wp":99.9,"hs":46,"as":24,"p":2,"text":"Aaron Bradshaw makes layup"},{"t":928,"wp":100.0,"hs":48,"as":24,"p":2,"text":"Karon Boyd makes 3-foot dunk (Will Berg assists)"},{"t":914,"wp":99.9,"hs":48,"as":26,"p":2,"text":"Simon Majok makes layup"},{"t":914,"wp":99.9,"hs":48,"as":27,"p":2,"text":"Simon Majok makes free throw 1 of 1"},{"t":899,"wp":100.0,"hs":50,"as":27,"p":2,"text":"Will Berg makes 2-foot dunk (Kenyon Giles assists)"},{"t":881,"wp":99.9,"hs":50,"as":29,"p":2,"text":"Simon Majok makes layup"},{"t":881,"wp":99.9,"hs":50,"as":30,"p":2,"text":"Simon Majok makes free throw 1 of 1"},{"t":823,"wp":99.8,"hs":50,"as":32,"p":2,"text":"Curtis Givens III makes 12-foot pullup jump shot (Quante Berry assists)"},{"t":779,"wp":99.6,"hs":50,"as":34,"p":2,"text":"Aaron Bradshaw makes driving layup (Curtis Givens III assists)"},{"t":757,"wp":99.9,"hs":52,"as":34,"p":2,"text":"Karon Boyd makes driving layup"},{"t":678,"wp":99.8,"hs":52,"as":36,"p":2,"text":"Zach Davis makes 7-foot jumper"},{"t":585,"wp":99.8,"hs":52,"as":37,"p":2,"text":"Curtis Givens III makes free throw 1 of 2"},{"t":585,"wp":99.7,"hs":52,"as":38,"p":2,"text":"Curtis Givens III makes free throw 2 of 2"},{"t":585,"wp":99.9,"hs":54,"as":38,"p":2,"text":"Kenyon Giles makes 8-foot floating jump shot (Dillon Battie assists)"},{"t":525,"wp":99.8,"hs":54,"as":40,"p":2,"text":"Zach Davis makes driving layup"},{"t":488,"wp":100.0,"hs":57,"as":40,"p":2,"text":"Dillon Battie makes 25-foot three point jumper"},{"t":475,"wp":99.9,"hs":57,"as":42,"p":2,"text":"Julius Thedford makes 3-foot jumper"},{"t":475,"wp":99.9,"hs":57,"as":43,"p":2,"text":"Julius Thedford makes free throw 1 of 1"},{"t":406,"wp":99.8,"hs":57,"as":45,"p":2,"text":"Zach Davis makes driving layup"},{"t":387,"wp":100.0,"hs":59,"as":45,"p":2,"text":"Karon Boyd makes driving layup"},{"t":328,"wp":99.8,"hs":59,"as":48,"p":2,"text":"Curtis Givens III makes 24-foot three point jumper (Julius Thedford assists)"},{"t":311,"wp":100.0,"hs":62,"as":48,"p":2,"text":"Karon Boyd makes 24-foot three point jumper (TJ Williams assists)"},{"t":296,"wp":100.0,"hs":62,"as":50,"p":2,"text":"Simon Majok makes 18-foot jumper (Curtis Givens III assists)"},{"t":271,"wp":100.0,"hs":64,"as":50,"p":2,"text":"Will Berg makes 1-foot dunk (TJ Williams assists)"},{"t":234,"wp":100.0,"hs":64,"as":52,"p":2,"text":"Curtis Givens III makes driving layup"},{"t":134,"wp":100.0,"hs":67,"as":52,"p":2,"text":"Karon Boyd makes 25-foot three point jumper (Will Berg assists)"},{"t":106,"wp":100.0,"hs":68,"as":52,"p":2,"text":"Dre Kindell makes free throw 1 of 2"},{"t":106,"wp":100.0,"hs":69,"as":52,"p":2,"text":"Dre Kindell makes free throw 2 of 2"},{"t":89,"wp":100.0,"hs":69,"as":54,"p":2,"text":"Curtis Givens III makes 7-foot floating jump shot"},{"t":49,"wp":100.0,"hs":72,"as":54,"p":2,"text":"Kenyon Giles makes 25-foot three point jumper"},{"t":47,"wp":100.0,"hs":72,"as":57,"p":2,"text":"Quante Berry makes 24-foot three point jumper"},{"t":36,"wp":100.0,"hs":74,"as":57,"p":2,"text":"Dre Kindell makes driving layup"},{"t":28,"wp":100.0,"hs":74,"as":59,"p":2,"text":"Simon Majok makes 1-foot dunk (Zach Davis assists)"},{"t":0,"wp":100.0,"hs":74,"as":59,"p":2,"text":"End of 2nd half"},{"t":0,"wp":100.0,"hs":74,"as":59,"p":2,"text":"End of Game"},{"t":0,"wp":100.0,"hs":74,"as":59,"p":2,"text":"Final"}],"runs":[{"team":"WICH","run":"12-0","pts":12,"period":1,"start_clock":"17:27","end_clock":"13:40","start_score":"0-4","end_score":"12-4"},{"team":"WICH","run":"11-0","pts":11,"period":1,"start_clock":"1:07","end_clock":"17:07","start_score":"35-22","end_score":"46-22"},{"team":"WICH","run":"10-0","pts":10,"period":1,"start_clock":"8:14","end_clock":"5:46","start_score":"19-8","end_score":"29-8"}],"lead_changes":1,"ties":6,"largest_lead":{"home":24,"away":4},"big_swings":[{"idx":6,"swing":5.9,"text":"Michael Gray Jr. makes 27-foot three point jumper (Kenyon Giles assists)","wp":70.5},{"idx":15,"swing":5.3,"text":"Brian Amuneke makes 24-foot three point jumper (Kenyon Giles assists)","wp":91.9},{"idx":13,"swing":4.5,"text":"Brian Amuneke makes 26-foot three point jumper (TJ Williams assists)","wp":88.7},{"idx":4,"swing":4.3,"text":"Kenyon Giles makes 17-foot pullup jump shot","wp":60.3},{"idx":5,"swing":4.3,"text":"Dillon Battie makes driving layup","wp":64.6}]}